gemini/__init__.py
gemini/async_client.py
gemini/client.py
gemini/src/__init__.py
gemini/src/extensions/__init__.py
gemini/src/extensions/replit.py
gemini/src/misc/__init__.py
gemini/src/misc/constants.py
gemini/src/misc/decorator.py
gemini/src/misc/exceptions.py
gemini/src/misc/utils.py
gemini/src/model/__init__.py
gemini/src/model/image.py
gemini/src/model/output.py
gemini/src/model/parser/__init__.py
gemini/src/model/parser/base.py
gemini/src/model/parser/custom_parser.py
gemini/src/model/parser/response_parser.py
gemini/src/modules/__init__.py
gemini/src/modules/openrouter/__init__.py
gemini/src/modules/openrouter/async_client.py
gemini/src/modules/openrouter/client.py
gemini/src/modules/openrouter/const.py
gemini/src/modules/voice/__init__.py
gemini/src/modules/voice/google.py
gemini/src/modules/voice/openai.py
python_gemini_api-2.4.12.dist-info/LICENSE
python_gemini_api-2.4.12.dist-info/METADATA
python_gemini_api-2.4.12.dist-info/WHEEL
python_gemini_api-2.4.12.dist-info/entry_points.txt
python_gemini_api-2.4.12.dist-info/top_level.txt
python_gemini_api-2.4.12.dist-info/RECORD
