Metadata-Version: 2.1
Name: python-gemini-api
Version: 2.4.12
Summary: The python package that returns Response of Google Gemini through API.
Home-page: https://github.com/dsdanielpark/Gemini-API
Author: Daniel Park
Author-email: parkminwoo1991@gmail.com
Keywords: Python,API,Gemini,Google Gemini,Large Language Model,Chatbot API,Google API,Chatbot
Classifier: Development Status :: 2 - Pre-Alpha
Classifier: Intended Audience :: Science/Research
Classifier: Natural Language :: English
Classifier: Programming Language :: Python
Classifier: Programming Language :: Python :: 3.9
Classifier: Programming Language :: Python :: 3.10
Classifier: Programming Language :: Python :: 3.11
Classifier: Programming Language :: Python :: 3.12
Classifier: License :: OSI Approved :: MIT License
Classifier: Topic :: Scientific/Engineering :: Artificial Intelligence
Requires-Python: >=3.9
License-File: LICENSE
Requires-Dist: httpx[http2]>=0.20.0
Requires-Dist: requests
Requires-Dist: browser_cookie3
Requires-Dist: loguru
Requires-Dist: pydantic
Requires-Dist: aiohttp
Provides-Extra: voice
Requires-Dist: gTTS; extra == "voice"
Requires-Dist: SpeechRecognition; extra == "voice"
Requires-Dist: openai; extra == "voice"
Requires-Dist: anthropic; extra == "voice"
